[
  {
    "title": "ADHD-skeptisk overlege: – Jeg håper ikke altfor mange blir krenket",
    "description": "Hun har stilt hundrevis av diagnoser. – Nå får jeg oftere og oftere en dårlig magefølelse, sier barnepsykiater Henriette K. Sandven.",
    "type": "Artikkel",
    "images": [
      { "image": "", "photographer": "", "alt": "Bilde av Henriette Sandven" }
    ],
    "date": "07.02.2025",
    "subscription": true,
    "publisher": {
      "logo": "",
      "title": "A-magasinet",
      "journalists": ["Bjørn Egil Halvorsen"]
    },
    "link": "https://www.aftenposten.no/amagasinet/i/vgGeA5/psykiater-henriette-k-sandven-ut-mot-adhd-diagnoser"
  }
]
